mnp/__init__.py
mnp/_stubs/mantik/mnp/mnp_pb2.py
mnp/_stubs/mantik/mnp/mnp_pb2_grpc.py
mnp/collectable_byte_buffer.py
mnp/elements.py
mnp/forwarder.py
mnp/handler.py
mnp/mnp_url.py
mnp/rpc_converter.py
mnp/server.py
mnp/service_server.py
mnp/session_handler.py
mnp/streammultiplexer.py
mnp-0.4.0.dist-info/WHEEL
mnp-0.4.0.dist-info/METADATA
mnp-0.4.0.dist-info/RECORD
