Metadata-Version: 2.1
Name: mnp
Version: 0.4.0
Summary: 
Home-page: https://www.mantik.ai
Author: Mantik Team
Author-email: info@mantik.ai
Requires-Python: >=3.7,<3.8
Classifier: Programming Language :: Python :: 3
Classifier: Programming Language :: Python :: 3.7
Requires-Dist: grpcio (>=1.37.1,<2.0.0)
Requires-Dist: grpcio-tools (>=1.37.1,<2.0.0)
Requires-Dist: protobuf (>=3.16.0,<4.0.0)
